aiy_voice/.board.py.kate-swp
aiy_voice/__init__.py
aiy_voice/board.py
aiy_voice/leds.py
aiy_voice/pins.py
aiy_voice/version.py
aiy_voice-0.0.1.dist-info/LICENSE
aiy_voice-0.0.1.dist-info/METADATA
aiy_voice-0.0.1.dist-info/WHEEL
aiy_voice-0.0.1.dist-info/top_level.txt
aiy_voice-0.0.1.dist-info/RECORD
